{
  "videoData": [
    {
      "lang": "en",
      "url": "https://download.mlcc.google.com/mledu-videos/en/neural_net_intro.mp4",
      "videoId": "a-L4qZ2Z6qc"
    },
    {
      "lang": "es-419",
      "url": "https://download.mlcc.google.com/mledu-videos/es-419/neural_net_intro.mp4",
      "videoId": "JAGeh4RpPjk"
    },
    {
      "lang": "fr",
      "url": "https://download.mlcc.google.com/mledu-videos/fr/neural_net_intro.mp4",
      "videoId": "f925JR1yRYM"
    },
    {
      "lang": "ko",
      "url": "https://download.mlcc.google.com/mledu-videos/ko/neural_net_intro.mp4",
      "videoId": "D-aRv1BkpYs"
    },
    {
      "lang": "zh-cn",
      "url": "https://download.mlcc.google.cn/mledu-videos/zh-cn/neural_net_intro.mp4",
      "videoId": "7CEiN2-2bh0"
    },
    {
      "lang": "id",
      "url": "https://download.mlcc.google.com/mledu-videos/id/neural_net_intro.mp4",
      "videoId": "3luPyQzwGLE"
    }
  ]
}
